bulk_task/__init__.py
bulk_task/backend.py
bulk_task/core.py
bulk_task/models.py
bulk_task/utils.py
bulk_task-0.0.2.dist-info/LICENSE
bulk_task-0.0.2.dist-info/METADATA
bulk_task-0.0.2.dist-info/WHEEL
bulk_task-0.0.2.dist-info/top_level.txt
bulk_task-0.0.2.dist-info/RECORD
