Metadata-Version: 2.1
Name: bulk-task
Version: 0.0.2
Summary: Celery bulk tasks
Home-page: https://github.com/buserbrasil/bulk-task
Author: Walison Filipe
Author-email: walisonfilipe@hotmail.com
License: MIT
Platform: UNKNOWN
Classifier: Development Status :: 3 - Alpha
Classifier: Intended Audience :: Developers
Classifier: License :: OSI Approved :: MIT License
Classifier: Operating System :: OS Independent
Classifier: Programming Language :: Python :: 3
Classifier: Programming Language :: Python :: 3 :: Only
Classifier: Topic :: Software Development :: Libraries :: Python Modules
License-File: LICENSE
